validating_models/__init__.py
validating_models/checker.py
validating_models/colors.py
validating_models/constraint.py
validating_models/dataset.py
validating_models/drawing_utils.py
validating_models/frequency_distribution_table.py
validating_models/logger.py
validating_models/shacl_validation_engine.py
validating_models/stats.py
validating_models/groupings/__init__.py
validating_models/groupings/classification.py
validating_models/groupings/decision_trees.py
validating_models/groupings/general.py
validating_models/groupings/random_forest.py
validating_models/models/__init__.py
validating_models/models/decision_tree.py
validating_models/models/random_forest.py
validating_models/visualizations/__init__.py
validating_models/visualizations/classification.py
validating_models/visualizations/decision_trees.py
validating_models/visualizations/ensembles.py
validating_models/visualizations/graphviz_helper.py
validating_models/visualizations/regression.py
validating_models-0.9.6.dist-info/LICENSE
validating_models-0.9.6.dist-info/METADATA
validating_models-0.9.6.dist-info/WHEEL
validating_models-0.9.6.dist-info/top_level.txt
validating_models-0.9.6.dist-info/RECORD
