Metadata-Version: 2.1
Name: validating-models
Version: 0.9.6
Summary: Supporting Explainable AI on Semantic Constraint Validation
Home-page: https://github.com/JulianLoewe/Validating_Models
Download-URL: https://github.com/JulianLoewe/Validating_Models/archive/refs/tags/v0.9.6.tar.gz
Author: Julian Gercke
License: GNU/GPLv3
Classifier: Development Status :: 4 - Beta
Classifier: Programming Language :: Python
Classifier: Programming Language :: Python :: 3
Classifier: Programming Language :: Python :: 3 :: Only
Classifier: Programming Language :: Python :: 3.8
Classifier: Programming Language :: Python :: 3.9
Classifier: Programming Language :: Python :: 3.10
Classifier: License :: OSI Approved :: GNU General Public License v3 (GPLv3)
Classifier: Operating System :: OS Independent
Classifier: Intended Audience :: Science/Research
Requires-Python: >=3.8
License-File: LICENSE
Requires-Dist: shaclapi >=0.11.0
Requires-Dist: cairosvg >=2.5.2
Requires-Dist: dtreeviz >=2.0.0
Requires-Dist: matplotlib
Requires-Dist: numpy
Requires-Dist: openml
Requires-Dist: pandas
Requires-Dist: Pillow
Requires-Dist: rdflib >=6.1.0
Requires-Dist: requests
Requires-Dist: scikit-learn
Requires-Dist: seaborn >=0.11.2
Requires-Dist: SPARQLWrapper >=2.0.0
Requires-Dist: tqdm >=4.63.0
Requires-Dist: pebble >=4.6.0
